pytensor/__init__.py
pytensor/_version.py
pytensor/breakpoint.py
pytensor/configdefaults.py
pytensor/configparser.py
pytensor/gradient.py
pytensor/ifelse.py
pytensor/ipython.py
pytensor/npy_2_compat.py
pytensor/printing.py
pytensor/py.typed
pytensor/raise_op.py
pytensor/updates.py
pytensor/utils.py
pytensor/bin/__init__.py
pytensor/bin/pytensor_cache.py
pytensor/compile/__init__.py
pytensor/compile/builders.py
pytensor/compile/compiledir.py
pytensor/compile/compilelock.py
pytensor/compile/debugmode.py
pytensor/compile/io.py
pytensor/compile/mode.py
pytensor/compile/monitormode.py
pytensor/compile/nanguardmode.py
pytensor/compile/ops.py
pytensor/compile/profiling.py
pytensor/compile/sharedvalue.py
pytensor/compile/function/__init__.py
pytensor/compile/function/pfunc.py
pytensor/compile/function/types.py
pytensor/d3viz/__init__.py
pytensor/d3viz/d3viz.py
pytensor/d3viz/formatting.py
pytensor/d3viz/css/d3-context-menu.css
pytensor/d3viz/css/d3viz.css
pytensor/d3viz/html/template.html
pytensor/d3viz/js/d3-context-menu.js
pytensor/d3viz/js/d3.v3.min.js
pytensor/d3viz/js/d3viz.js
pytensor/d3viz/js/dagre-d3.min.js
pytensor/d3viz/js/graphlib-dot.min.js
pytensor/graph/__init__.py
pytensor/graph/basic.py
pytensor/graph/destroyhandler.py
pytensor/graph/features.py
pytensor/graph/fg.py
pytensor/graph/null_type.py
pytensor/graph/op.py
pytensor/graph/replace.py
pytensor/graph/traversal.py
pytensor/graph/type.py
pytensor/graph/utils.py
pytensor/graph/rewriting/__init__.py
pytensor/graph/rewriting/basic.py
pytensor/graph/rewriting/db.py
pytensor/graph/rewriting/kanren.py
pytensor/graph/rewriting/unify.py
pytensor/graph/rewriting/utils.py
pytensor/link/__init__.py
pytensor/link/basic.py
pytensor/link/utils.py
pytensor/link/vm.py
pytensor/link/c/__init__.py
pytensor/link/c/basic.py
pytensor/link/c/cmodule.py
pytensor/link/c/cutils.py
pytensor/link/c/cvm.py
pytensor/link/c/exceptions.py
pytensor/link/c/interface.py
pytensor/link/c/lazylinker_c.py
pytensor/link/c/op.py
pytensor-2.37.0.dist-info/licenses/LICENSE.txt
pytensor-2.37.0.dist-info/METADATA
pytensor-2.37.0.dist-info/WHEEL
pytensor-2.37.0.dist-info/entry_points.txt
pytensor-2.37.0.dist-info/top_level.txt
pytensor-2.37.0.dist-info/RECORD
