Metadata-Version: 2.4
Name: pytensor
Version: 2.37.0
Summary: Optimizing compiler for evaluating mathematical expressions on CPUs and GPUs.
Author-email: pymc-devs <pymc.devs@gmail.com>
License-Expression: BSD-3-Clause
Project-URL: homepage, https://github.com/pymc-devs/pytensor
Project-URL: repository, https://github.com/pymc-devs/pytensor
Project-URL: documentation, https://pytensor.readthedocs.io/en/latest/
Keywords: pytensor,math,numerical,symbolic,blas,numpy,autodiff,differentiation
Classifier: Development Status :: 6 - Mature
Classifier: Intended Audience :: Education
Classifier: Intended Audience :: Science/Research
Classifier: Intended Audience :: Developers
Classifier: Programming Language :: Python
Classifier: Topic :: Software Development :: Code Generators
Classifier: Topic :: Software Development :: Compilers
Classifier: Topic :: Scientific/Engineering :: Mathematics
Classifier: Operating System :: Microsoft :: Windows
Classifier: Operating System :: POSIX
Classifier: Operating System :: Unix
Classifier: Operating System :: MacOS
Classifier: Programming Language :: Python :: 3
Classifier: Programming Language :: Python :: 3.11
Classifier: Programming Language :: Python :: 3.12
Classifier: Programming Language :: Python :: 3.13
Classifier: Programming Language :: Python :: 3.14
Requires-Python: <3.15,>=3.11
License-File: LICENSE.txt
Requires-Dist: setuptools>=59.0.0
Requires-Dist: scipy<2,>=1
Requires-Dist: numpy>=2.0
Requires-Dist: numba<1,>0.57
Requires-Dist: filelock>=3.15
Requires-Dist: etuples
Requires-Dist: logical-unification
Requires-Dist: miniKanren
Requires-Dist: cons
Provides-Extra: complete
Requires-Dist: pytensor[jax]; extra == "complete"
Requires-Dist: pytensor[numba]; extra == "complete"
Provides-Extra: development
Requires-Dist: pytensor[complete]; extra == "development"
Requires-Dist: pytensor[tests]; extra == "development"
Requires-Dist: pytensor[rtd]; extra == "development"
Provides-Extra: tests
Requires-Dist: pytest; extra == "tests"
Requires-Dist: pre-commit; extra == "tests"
Requires-Dist: pytest-cov>=2.6.1; extra == "tests"
Requires-Dist: coverage>=5.1; extra == "tests"
Requires-Dist: pytest-benchmark; extra == "tests"
Requires-Dist: pytest-mock; extra == "tests"
Requires-Dist: pytest-sphinx; extra == "tests"
Provides-Extra: rtd
Requires-Dist: sphinx<6,>=5.1.0; extra == "rtd"
Requires-Dist: pygments; extra == "rtd"
Requires-Dist: pydot; extra == "rtd"
Provides-Extra: jax
Requires-Dist: jax; extra == "jax"
Requires-Dist: jaxlib; extra == "jax"
Provides-Extra: numba
Requires-Dist: numba>=0.57; extra == "numba"
Requires-Dist: llvmlite; extra == "numba"
Dynamic: license-file
